{
  "_fv": 18,
  "_type": "food",
  "definition": {
    "renderType": 0,
    "texture": "cheat_food",
    "customModelName": "Normal",
    "name": "Plexra Food",
    "rarity": "EPIC",
    "specialInfo": [
      "La nourriture ULTIME!! (Mieux qu'un pomme de notch)."
    ],
    "creativeTab": {
      "value": "CUSTOM:Ongletplexielmod"
    },
    "stackSize": 64,
    "nutritionalValue": 1000,
    "saturation": 1000.0,
    "eatingSpeed": 32,
    "resultItem": {
      "value": ""
    },
    "forDogs": false,
    "isAlwaysEdible": true,
    "animation": "eat",
    "hasGlow": false,
    "onEaten": {
      "name": "PlexrafoodQuandLaNourritureEstMangee"
    }
  }
}